Metadata-Version: 1.0
Name: jzrkingsta-prob
Version: 0.1
Summary: Gaussian and Binomial distributions
Home-page: UNKNOWN
Author: James L Zhang
Author-email: jzr.kingsta@outlook.com
License: UNKNOWN
Platform: UNKNOWN
